campbell_quest/__init__.py
campbell_quest/dialogue_generator.py
campbell_quest/enemy_generator.py
campbell_quest/item_generator.py
campbell_quest/quest_generator.py
campbell_quest/dialogueAgents/__init__.py
campbell_quest/dialogueAgents/dialogue_brainstormer.py
campbell_quest/dialogueAgents/dialogue_formatter.py
campbell_quest/dialogueAgents/dialogue_refiner.py
campbell_quest/enemyAgents/__init__.py
campbell_quest/enemyAgents/enemy_brainstormer.py
campbell_quest/enemyAgents/enemy_formatter.py
campbell_quest/enemyAgents/enemy_refiner.py
campbell_quest/itemAgents/__init__.py
campbell_quest/itemAgents/item_brainstormer.py
campbell_quest/itemAgents/item_formatter.py
campbell_quest/itemAgents/item_refiner.py
campbell_quest/questAgents/__init__.py
campbell_quest/questAgents/quest_brainstormer.py
campbell_quest/questAgents/quest_formatter.py
campbell_quest/questAgents/quest_refiner.py
campbell_quest-0.0.31.dist-info/LICENSE
campbell_quest-0.0.31.dist-info/METADATA
campbell_quest-0.0.31.dist-info/WHEEL
campbell_quest-0.0.31.dist-info/top_level.txt
campbell_quest-0.0.31.dist-info/RECORD
