Metadata-Version: 2.1
Name: campbell_quest
Version: 0.0.31
Summary: A procedural quest generation system.
Author-email: Jasfiq Rahman <jasfiqrahman15@gmail.com>
Project-URL: Homepage, https://github.com/pypa/sampleproject
Project-URL: Issues, https://github.com/pypa/sampleproject/issues
Classifier: Programming Language :: Python :: 3
Classifier: License :: OSI Approved :: MIT License
Classifier: Operating System :: OS Independent
Requires-Python: >=3.8
License-File: LICENSE
Requires-Dist: ollama
Requires-Dist: langchain-community
